ssec_amqp/__about__.py
ssec_amqp/__init__.py
ssec_amqp/_retry.py
ssec_amqp/amqp.py
ssec_amqp/api.py
ssec_amqp/client.py
ssec_amqp/py.typed
ssec_amqp/utils.py
quickmq-2.0.0.dist-info/METADATA
quickmq-2.0.0.dist-info/WHEEL
quickmq-2.0.0.dist-info/licenses/LICENSE
quickmq-2.0.0.dist-info/RECORD
