Metadata-Version: 2.3
Name: quickmq
Version: 2.0.0
Summary: A RabbitMQ client for the SSEC.
Project-URL: source, https://gitlab.ssec.wisc.edu/mdrexler/ssec_amqp
Project-URL: issues, https://gitlab.ssec.wisc.edu/mdrexler/ssec_amqp/-/issues
Project-URL: changes, https://gitlab.ssec.wisc.edu/mdrexler/ssec_amqp/-/blob/main/CHANGELOG?ref_type=heads
Author-email: Max Drexler <mndrexler@wisc.com>
License: MIT
Keywords: AMQP,RabbitMQ,SDS,SSEC
Classifier: Development Status :: 4 - Beta
Classifier: Intended Audience :: Developers
Classifier: License :: OSI Approved :: MIT License
Classifier: Natural Language :: English
Classifier: Operating System :: POSIX :: Linux
Classifier: Programming Language :: Python
Classifier: Programming Language :: Python :: 3.6
Classifier: Programming Language :: Python :: 3.7
Classifier: Programming Language :: Python :: 3.8
Classifier: Programming Language :: Python :: 3.9
Classifier: Programming Language :: Python :: 3.10
Classifier: Programming Language :: Python :: 3.11
Classifier: Programming Language :: Python :: 3.12
Classifier: Programming Language :: Python :: 3.13
Classifier: Programming Language :: Python :: Implementation :: CPython
Classifier: Typing :: Typed
Requires-Python: >=3.6
Requires-Dist: amqp<=5.2.0
Requires-Dist: typing-extensions; python_version < '3.10'
